README.txt
setup.py
AlertLogicAPI/Exceptions.py
AlertLogicAPI/__init__.py
AlertLogicAPI.egg-info/PKG-INFO
AlertLogicAPI.egg-info/SOURCES.txt
AlertLogicAPI.egg-info/dependency_links.txt
AlertLogicAPI.egg-info/requires.txt
AlertLogicAPI.egg-info/top_level.txt