Metadata-Version: 1.1
Name: AlertLogicAPI
Version: 0.0.4
Summary: Alert Logic API
Home-page: https://github.com/freimer/AlertLogicAPI
Author: Frederick Reimer
Author-email: freimer@freimer.org
License: GPL v3
Platform: Posix; MacOS X; Windows
Classifier: Development Status :: 3 - Alpha
Classifier: Intended Audience :: Developers
Classifier: Intended Audience :: System Administrators
Classifier: License :: OSI Approved :: GNU General Public License v3 (GPLv3)
Classifier: Operating System :: OS Independent
Classifier: Topic :: System :: Networking :: Monitoring
